ppulp/__init__.py
ppulp/problem.py
ppulp/utils.py
tests/__init__.py
tests/test_ppulp.py
tests/tutorials/__init__.py
tests/tutorials/test_partitioning_problem.py
tests/tutorials/test_problem_descriptions.py
tests/tutorials/test_sudoku.py
tests/tutorials/test_transportation_problem.py
tests/tutorials/test_two_stage_production_planning_problem.py
ppulp-0.1.0.dist-info/LICENSE
ppulp-0.1.0.dist-info/METADATA
ppulp-0.1.0.dist-info/WHEEL
ppulp-0.1.0.dist-info/top_level.txt
ppulp-0.1.0.dist-info/RECORD
