Metadata-Version: 2.1
Name: ppulp
Version: 0.1.0
Summary: An extension of PuLP, a linear programming problem modeling tool
Home-page: UNKNOWN
Author: nariaki tateiwa
Author-email: nariaki3551@gmail.com
License: MIT
Keywords: optimization LP linear programming modeling
Platform: UNKNOWN
Classifier: License :: OSI Approved :: MIT License
Classifier: Programming Language :: Python :: 3.8
Classifier: Programming Language :: Python :: 3.9
Classifier: Programming Language :: Python :: 3.10
License-File: LICENSE
Requires-Dist: numpy
Requires-Dist: pulp
Requires-Dist: flopt (>=0.5.5)
